skpp/__init__.py
skpp/skpp.py
skpp/tests/__init__.py
skpp/tests/test_skpp.py
projection_pursuit-1.1.dist-info/LICENSE
projection_pursuit-1.1.dist-info/METADATA
projection_pursuit-1.1.dist-info/WHEEL
projection_pursuit-1.1.dist-info/top_level.txt
projection_pursuit-1.1.dist-info/RECORD
