Metadata-Version: 2.1
Name: projection-pursuit
Version: 1.1
Summary: Scikit-learn estimators based on projection pursuit
Author-email: Pavel Komarov <pvlkmrv@gmail.com>
License: BSD License
Project-URL: Documentation, https://pavelkomarov.como/projection-pursuit
Project-URL: Repository, https://github.com/pavelkomarov/projection-pursuit
License-File: LICENSE
Requires-Dist: pytest
Requires-Dist: numpy
Requires-Dist: scikit-learn
Requires-Dist: matplotlib
